odoo_test_loop/__about__.py
odoo_test_loop/__init__.py
odoo_test_loop/cli.py
odoo_test_loop-0.0.2.dist-info/METADATA
odoo_test_loop-0.0.2.dist-info/WHEEL
odoo_test_loop-0.0.2.dist-info/entry_points.txt
odoo_test_loop-0.0.2.dist-info/licenses/LICENSE.txt
odoo_test_loop-0.0.2.dist-info/RECORD
