Metadata-Version: 2.3
Name: odoo-test-loop
Version: 0.0.2
Project-URL: Documentation, https://github.com/micdahl/odoo-test-loop#readme
Project-URL: Issues, https://github.com/micdahl/odoo-test-loop/issues
Project-URL: Source, https://github.com/micdahl/odoo-test-loop
Author-email: Michael Dahl <michael@dahl.software>
License: MIT
Classifier: Development Status :: 4 - Beta
Classifier: Programming Language :: Python
Classifier: Programming Language :: Python :: 3.8
Classifier: Programming Language :: Python :: 3.9
Classifier: Programming Language :: Python :: 3.10
Classifier: Programming Language :: Python :: 3.11
Classifier: Programming Language :: Python :: 3.12
Classifier: Programming Language :: Python :: Implementation :: CPython
Classifier: Programming Language :: Python :: Implementation :: PyPy
Requires-Python: >=3.8
Requires-Dist: odoo
Requires-Dist: typer
Requires-Dist: watchdog
